clenshawpy/__init__.py
clenshawpy-0.1.0.dist-info/LICENCE
clenshawpy-0.1.0.dist-info/METADATA
clenshawpy-0.1.0.dist-info/WHEEL
clenshawpy-0.1.0.dist-info/top_level.txt
clenshawpy-0.1.0.dist-info/RECORD
