Metadata-Version: 2.1
Name: clenshawpy
Version: 0.1.0
Summary: A package for representing and evaluating Clenshaw polynomials.
Home-page: https://github.com/yourusername/clenshawpy
Author: Your Name
Author-email: Alireza Afroozi <afrzi@proton.me>
Project-URL: Homepage, https://github.com/apri-me/clenshawpy
Keywords: clenshaw,polynomial,chebyshev,legendre,hermite,jacobi,math
Classifier: Programming Language :: Python :: 3
Classifier: Programming Language :: Python :: 3.6
Classifier: License :: OSI Approved :: MIT License
Classifier: Operating System :: OS Independent
Requires-Python: >=3.6
License-File: LICENCE
Requires-Dist: numpy
